aidash_ds_utils/__init__.py
aidash_ds_utils/core.py
aidash_ds_utils-0.2.2.dist-info/licenses/LICENSE
aidash_ds_utils-0.2.2.dist-info/METADATA
aidash_ds_utils-0.2.2.dist-info/WHEEL
aidash_ds_utils-0.2.2.dist-info/top_level.txt
aidash_ds_utils-0.2.2.dist-info/RECORD
