Metadata-Version: 2.4
Name: aidash_ds_utils
Version: 0.2.2
Summary: AiDash utilities for geospatial data science. Prioritize and clip overlapping geospatial masks.
Author-email: Shantanu Rajora <shantanu@aidash.com>
License: MIT
Classifier: Programming Language :: Python :: 3
Classifier: License :: OSI Approved :: MIT License
Classifier: Operating System :: OS Independent
Requires-Python: >=3.7
License-File: LICENSE
Requires-Dist: geopandas
Requires-Dist: pandas
Requires-Dist: shapely
Dynamic: license-file
